mysale_api/__init__.py
mysale_api/client.py
mysale_api/exceptions.py
mysale_api/throttler.py
mysale_api/utils.py
mysale_api/models/__init__.py
mysale_api/models/order.py
mysale_api/models/product.py
mysale_api/models/returns.py
mysale_api/models/shipping.py
mysale_api/models/sku.py
mysale_api/models/taxonomy.py
mysale_api/resources/__init__.py
mysale_api/resources/base.py
mysale_api/resources/order.py
mysale_api/resources/product.py
mysale_api/resources/returns.py
mysale_api/resources/shipping.py
mysale_api/resources/sku.py
mysale_api/resources/taxonomy.py
mysale_api_sdk-0.1.2.dist-info/licenses/LICENCE
mysale_api_sdk-0.1.2.dist-info/METADATA
mysale_api_sdk-0.1.2.dist-info/WHEEL
mysale_api_sdk-0.1.2.dist-info/top_level.txt
mysale_api_sdk-0.1.2.dist-info/RECORD
