Metadata-Version: 2.4
Name: mysale-api-sdk
Version: 0.1.2
Summary: Python SDK for MySale Marketplace API integration
Author-email: Benjamin Herro <benjamincsherro@hotmail.com>
License: MIT
Project-URL: Homepage, https://github.com/DuneRaccoon/mysale-api-sdk
Project-URL: Repository, https://github.com/DuneRaccoon/mysale-api-sdk
Project-URL: Documentation, https://apacsale.atlassian.net/wiki/spaces/MPS/pages/2109931778/API+Documentation
Project-URL: Bug Reports, https://github.com/DuneRaccoon/mysale-api-sdk/issues
Keywords: mysale,ozsale,marketplace,api,sdk,ecommerce
Classifier: Development Status :: 4 - Beta
Classifier: Intended Audience :: Developers
Classifier: License :: OSI Approved :: MIT License
Classifier: Operating System :: OS Independent
Classifier: Programming Language :: Python :: 3
Classifier: Programming Language :: Python :: 3.10
Classifier: Programming Language :: Python :: 3.11
Classifier: Programming Language :: Python :: 3.12
Classifier: Topic :: Internet :: WWW/HTTP :: Dynamic Content
Classifier: Topic :: Software Development :: Libraries :: Python Modules
Classifier: Topic :: Office/Business
Classifier: Topic :: Software Development :: Libraries :: Application Frameworks
Requires-Python: >=3.10
License-File: LICENCE
Requires-Dist: typing-extensions>=4.0.0
Requires-Dist: leaky-bucket-py<0.2.0,>=0.1.3
Requires-Dist: pydantic<3.0.0,>=2.11.7
Requires-Dist: httpx<0.29.0,>=0.28.1
Provides-Extra: dev
Requires-Dist: pytest>=7.0.0; extra == "dev"
Requires-Dist: pytest-asyncio>=0.21.0; extra == "dev"
Requires-Dist: pytest-cov>=4.0.0; extra == "dev"
Requires-Dist: black>=23.0.0; extra == "dev"
Requires-Dist: isort>=5.0.0; extra == "dev"
Requires-Dist: flake8>=6.0.0; extra == "dev"
Requires-Dist: mypy>=1.0.0; extra == "dev"
Dynamic: license-file
